README
setup.py
spreadsheet_maker/__init__.py
spreadsheet_maker/spreadsheet_maker.py
spreadsheet_maker.egg-info/PKG-INFO
spreadsheet_maker.egg-info/SOURCES.txt
spreadsheet_maker.egg-info/dependency_links.txt
spreadsheet_maker.egg-info/top_level.txt