Metadata-Version: 1.1
Name: spreadsheet-maker
Version: 1.0
Summary: Simple framework to create Google Spreadsheet with python
Home-page: https://github.com/HolmesInc/spreadsheet_maker.git
Author: Andrew Babenko
Author-email: andruonline11@gmail.com
License: LICENSE
Keywords: 'google-spreadsheet','spreadsheet','create-google-spreadsheet'
Platform: UNKNOWN
Classifier: Intended Audience :: Developers
Classifier: Programming Language :: Python
Classifier: License :: OSI Approved :: Apache Software License
Classifier: Operating System :: OS Independent
Classifier: Topic :: Software Development
Classifier: Topic :: Software Development :: Libraries :: Python Modules
Classifier: Topic :: Office/Business :: Financial :: Spreadsheet
